Metadata-Version: 1.0
Name: herecomes
Version: 0.0.1
Summary: Here comes a new challenger
Home-page: https://github.com/alvations/herecomes
Author: UNKNOWN
Author-email: UNKNOWN
License: UNKNOWN
Platform: UNKNOWN
